pvtlib/__init__.py
pvtlib/aga8.py
pvtlib/fluid_mechanics.py
pvtlib/thermodynamics.py
pvtlib/unit_converters.py
pvtlib/utilities.py
pvtlib/equipment/__init__.py
pvtlib/equipment/separators.py
pvtlib/equipment/valves.py
pvtlib/metering/__init__.py
pvtlib/metering/coriolis_flowmeters.py
pvtlib/metering/differential_pressure_flowmeters.py
pvtlib/metering/gas_density_meters.py
pvtlib/metering/level_measurement.py
pvtlib/metering/ultrasonic_flowmeters.py
pvtlib-1.11.0.dist-info/licenses/LICENSE
tests/__init__.py
tests/test_aga8.py
tests/test_differential_pressure_flowmeters.py
tests/test_fluid_mechanics.py
tests/test_gas_density_meters.py
tests/test_level_measurement.py
tests/test_separators.py
tests/test_thermodynamics.py
tests/test_unit_converters.py
tests/test_utilities.py
tests/test_valves.py
tests/test_venturi_wetgas_corrections.py
pvtlib-1.11.0.dist-info/METADATA
pvtlib-1.11.0.dist-info/WHEEL
pvtlib-1.11.0.dist-info/top_level.txt
pvtlib-1.11.0.dist-info/RECORD
