Metadata-Version: 2.4
Name: pvtlib
Version: 1.11.0
Summary: A library containing various tools in the categories of thermodynamics, fluid mechanics, metering etc.
Home-page: https://github.com/equinor/pvtlib
Author: Christian Hågenvik
Author-email: chaagen2013@gmail.com
License: MIT
Keywords: thermodynamics fluid-mechanics metering aga8
Classifier: Programming Language :: Python :: 3
Classifier: License :: OSI Approved :: MIT License
Classifier: Operating System :: OS Independent
Requires-Python: >=3.9
License-File: LICENSE
Requires-Dist: numpy>=1.26.2
Requires-Dist: scipy>=1.11.4
Requires-Dist: pyaga8>=0.1.15
Dynamic: author
Dynamic: author-email
Dynamic: classifier
Dynamic: description
Dynamic: description-content-type
Dynamic: home-page
Dynamic: keywords
Dynamic: license
Dynamic: license-file
Dynamic: requires-dist
Dynamic: requires-python
Dynamic: summary
